thunderpath/__about__.py
thunderpath/__init__.py
thunderpath/__main__.py
thunderpath/cli/__init__.py
thunderpath-0.0.0.dev3.dist-info/METADATA
thunderpath-0.0.0.dev3.dist-info/WHEEL
thunderpath-0.0.0.dev3.dist-info/entry_points.txt
thunderpath-0.0.0.dev3.dist-info/licenses/LICENSE
thunderpath-0.0.0.dev3.dist-info/RECORD
